poexy_core-2025.7.4.data/purelib/poexy_core/pyproject/tables/license.py
poexy_core-2025.7.4.data/purelib/poexy_core/metadata/builder.py
poexy_core-2025.7.4.data/purelib/poexy_core/manifest/types.py
poexy_core-2025.7.4.data/purelib/poexy_core/pyproject/exceptions.py
poexy_core-2025.7.4.data/purelib/poexy_core/pyproject/tables/package.py
poexy_core-2025.7.4.data/purelib/poexy_core/builders/hooks/package_files.py
poexy_core-2025.7.4.data/purelib/poexy_core/pyproject/toml.py
poexy_core-2025.7.4.data/purelib/poexy_core/builders/hooks/hook.py
poexy_core-2025.7.4.data/purelib/poexy_core/pyinstaller/argument_builder.py
poexy_core-2025.7.4.data/purelib/poexy_core/pyinstaller/builder.py
poexy_core-2025.7.4.data/purelib/poexy_core/packages/validators.py
poexy_core-2025.7.4.data/purelib/poexy_core/api.py
poexy_core-2025.7.4.data/purelib/poexy_core/builders/wheel.py
poexy_core-2025.7.4.data/purelib/poexy_core/utils/python_impl.py
poexy_core-2025.7.4.data/purelib/poexy_core/manifest/parser.py
poexy_core-2025.7.4.data/purelib/poexy_core/pyproject/types.py
poexy_core-2025.7.4.data/purelib/poexy_core/builders/sdist.py
poexy_core-2025.7.4.data/purelib/poexy_core/utils/subprocess_rt.py
poexy_core-2025.7.4.data/purelib/poexy_core/packages/format.py
poexy_core-2025.7.4.data/purelib/poexy_core/builders/hooks/include_files.py
poexy_core-2025.7.4.data/purelib/poexy_core/builders/types.py
poexy_core-2025.7.4.data/purelib/poexy_core/pyinstaller/types.py
poexy_core-2025.7.4.data/purelib/poexy_core/builders/hooks/license.py
poexy_core-2025.7.4.data/purelib/poexy_core/packages/package.py
poexy_core-2025.7.4.data/purelib/poexy_core/packages/files.py
poexy_core-2025.7.4.data/purelib/poexy_core/manifest/manifest.py
poexy_core-2025.7.4.data/purelib/poexy_core/builders/hooks/readme.py
poexy_core-2025.7.4.data/purelib/poexy_core/pyproject/tables/readme.py
poexy_core-2025.7.4.data/purelib/poexy_core/metadata/fields.py
poexy_core-2025.7.4.data/purelib/poexy_core/pyproject/tables/poexy.py
poexy_core-2025.7.4.dist-info/licenses/LICENSE
poexy_core-2025.7.4.dist-info/METADATA
poexy_core-2025.7.4.dist-info/WHEEL
poexy_core-2025.7.4.dist-info/RECORD
