Metadata-Version: 2.4
Name: poexy-core
Version: 2025.7.4
Summary: Unified Python packaging backend for wheels, sdist, and executables
Classifier: Programming Language :: Python :: 3
Classifier: Programming Language :: Python :: 3.9
Classifier: Programming Language :: Python :: 3.10
Classifier: Programming Language :: Python :: 3.11
Classifier: Programming Language :: Python :: 3.12
Classifier: Programming Language :: Python :: 3.13
Requires-Python: >=3.9,<3.14
Requires-Dist: poetry-core (>=2.1.0)
Requires-Dist: pydantic (>=2.11.7)
Requires-Dist: pyinstaller (>=6.14.2)
Requires-Dist: rich (>=14.0.0)
Requires-Dist: virtualenv (>=20.31.2)
